pyvisionai/__init__.py
pyvisionai/cli/__init__.py
pyvisionai/cli/describe_image.py
pyvisionai/cli/extract.py
pyvisionai/config/html_config.py
pyvisionai/core/__init__.py
pyvisionai/core/extractor.py
pyvisionai/core/factory.py
pyvisionai/describers/__init__.py
pyvisionai/describers/base.py
pyvisionai/describers/claude.py
pyvisionai/describers/ollama.py
pyvisionai/describers/openai.py
pyvisionai/extractors/__init__.py
pyvisionai/extractors/base.py
pyvisionai/extractors/docx.py
pyvisionai/extractors/docx_page.py
pyvisionai/extractors/html/browser.py
pyvisionai/extractors/html_page.py
pyvisionai/extractors/pdf.py
pyvisionai/extractors/pdf_page.py
pyvisionai/extractors/pptx.py
pyvisionai/extractors/pptx_page.py
pyvisionai/utils/__init__.py
pyvisionai/utils/benchmark.py
pyvisionai/utils/config.py
pyvisionai/utils/logger.py
pyvisionai/utils/retry.py
pyvisionai-0.3.1.dist-info/LICENSE
pyvisionai-0.3.1.dist-info/METADATA
pyvisionai-0.3.1.dist-info/WHEEL
pyvisionai-0.3.1.dist-info/entry_points.txt
pyvisionai-0.3.1.dist-info/RECORD
