Metadata-Version: 2.3
Name: pyvisionai
Version: 0.3.1
Summary: A Python library for extracting and describing content from documents using Vision LLMs
License: Apache-2.0
Keywords: pdf,docx,pptx,html,vision,llm,extraction
Author: MDGrey33
Author-email: roland@abouyounes.com
Requires-Python: >=3.11,<4.0
Classifier: Development Status :: 4 - Beta
Classifier: Intended Audience :: Developers
Classifier: License :: OSI Approved :: Apache Software License
Classifier: Programming Language :: Python :: 3
Classifier: Programming Language :: Python :: 3.11
Classifier: Programming Language :: Python :: 3.12
Classifier: Programming Language :: Python :: 3.13
Requires-Dist: anthropic (>=0.45.2,<0.46.0)
Requires-Dist: ollama (>=0.4.2,<0.5.0)
Requires-Dist: openai (>=1.58.1,<2.0.0)
Requires-Dist: pdf2image (>=1.17.0,<2.0.0)
Requires-Dist: pdfminer-six (>=20231228,<20231229)
Requires-Dist: pillow (>=11.0.0,<12.0.0)
Requires-Dist: playwright (>=1.41.0,<2.0.0)
Requires-Dist: pypdf (>=4.1.0,<5.0.0)
Requires-Dist: python-docx (>=1.1.2,<2.0.0)
Requires-Dist: python-pptx (>=1.0.2,<2.0.0)
Requires-Dist: requests (>=2.32.3,<3.0.0)
Project-URL: Repository, https://github.com/MDGrey33/pyvisionai
